oauth2_client/__init__.py
oauth2_client/credentials_manager.py
oauth2_client/http_server.py
oauth2_client-1.4.2.dist-info/LICENSE
oauth2_client-1.4.2.dist-info/METADATA
oauth2_client-1.4.2.dist-info/WHEEL
oauth2_client-1.4.2.dist-info/top_level.txt
oauth2_client-1.4.2.dist-info/RECORD
