Metadata-Version: 2.1
Name: oauth2-client
Version: 1.4.2
Summary: A client library for OAuth2
Home-page: http://github.com/antechrestos/OAuth2Client
Author: Benjamin Einaudi
Author-email: antechrestos@gmail.com
License: UNKNOWN
Platform: UNKNOWN
Classifier: Programming Language :: Python
Classifier: Natural Language :: English
Classifier: Operating System :: OS Independent
Classifier: Programming Language :: Python :: 3
Classifier: Programming Language :: Python :: 3.7
Classifier: Programming Language :: Python :: 3.8
Classifier: Programming Language :: Python :: 3.9
Classifier: Programming Language :: Python :: 3.10
Classifier: Topic :: Communications
License-File: LICENSE
